fenix/__init__.py
fenix/exceptions.py
fenix/session.py
fenix/utils.py
fenixapi-0.0.3.dist-info/LICENSE
fenixapi-0.0.3.dist-info/METADATA
fenixapi-0.0.3.dist-info/WHEEL
fenixapi-0.0.3.dist-info/top_level.txt
fenixapi-0.0.3.dist-info/RECORD
